Metadata-Version: 2.1
Name: simple-face-alignment
Version: 0.0.2
Summary: a simple implmentation for face align
Home-page: https://github.com/wrenchzc/simple-face-alignment
Author: Zhang, Chi
Author-email: wrench@outlook.com
License: UNKNOWN
Keywords: face alignment
Platform: UNKNOWN
Classifier: Programming Language :: Python :: 3
Classifier: License :: OSI Approved :: MIT License
Classifier: Operating System :: POSIX
Classifier: Operating System :: Microsoft :: Windows
Classifier: Operating System :: MacOS :: MacOS X
Classifier: Environment :: Console
Classifier: Intended Audience :: Developers
Classifier: Intended Audience :: Education
Classifier: Natural Language :: English
Classifier: Programming Language :: Python :: 3.6
Classifier: Programming Language :: Python :: 3.7
Classifier: Programming Language :: Python :: 3.8
Classifier: Programming Language :: Python :: 3.9
